Workbook

Sheet Index
A1: StressLens CCAR POC: Reference Workbook
A2: Companion to the PRD. All data is synthetic; the bank (Iris Demo Bancorp) is fictional. Reports are styled on FR Y-14 and are not regulatory submissions.
A3: Clean (curated) input files for squads B, C and D are in the repo folder data/curated/. Raw files with defects are in data/landing/.
A5: PLAN
A6: Requirements | B6: 19 business requirements with priority and acceptance criteria
A7: User Stories | B7: 16 stories by squad: acceptance criteria, dependencies, Gherkin scenarios
A8: Test Scenarios | B8: Every Gherkin scenario as a test checklist (QA fills in results)
A10: DATA MODEL AND MAPPING
A11: Tables Overview | B11: All tables with keys
A12: Data Dictionary | B12: Every field: description, type, example
A13: Mapping (M01-M16) | B13: Source-to-target mapping rules
A14: Code Map | B14: Product, status and collateral code mappings
A16: DATA QUALITY AND RECONCILIATION
A17: Seeded Defects | B17: The 12 planted data problems and how to find and fix each
A18: DQ Dimensions | B18: Completeness, accuracy, validity, uniqueness, integrity
A19: DQ Rules | B19: 15 rules with expected exceptions on the raw data
A20: DQ Exception Workflow | B20: How an exception moves from open to closed
A21: Recon Checks | B21: 8 reconciliation checks with expected results
A22: Recon Bridge | B22: Source file to curated to GL balance bridge
A23: Controls | B23: 12 key controls and their evidence
A25: CALCULATIONS AND REPORTING
A26: Scenarios | B26: Baseline, Moderate, Severe variables
A27: Parameters | B27: PD, LGD, CCF, risk-weight and other parameters
A28: Worked Examples | B28: Hand-checkable loan calculations
A29: Report R1 Fields | B29: Y-14Q-style loan extract fields
A30: Report R2 Lines | B30: Y-14A-style capital summary lines
A31: Edit Checks | B31: Report validation rules
A32: Report Recon Rules | B32: Report-level reconciliations
A34: SAMPLE DATA AND ANSWER KEY
A35: Data - Customer | B35: Raw customer file
A36: Data - Loan | B36: Raw loan file
A37: Data - Balance | B37: Raw balance file
A38: Data - Status | B38: Raw status history
A39: Data - Collateral | B39: Raw collateral file
A40: Data - GL Control | B40: GL control totals
A41: Expected Results | B41: 120-row QA answer key
A42: Expected Summary | B42: Portfolio totals by scenario (live formulas)

Sheet Requirements
A1: ID | B1: Requirement | C1: Business rationale | D1: Priority | E1: Acceptance criteria | F1: Dependencies
A2: BR-001 | B2: Load the 5 source files and the GL control file for a given as-of date into staging, tagging every row with a batch ID and load timestamp | C2: CCAR numbers must be traceable to a specific source delivery | D2: Must | E2: All 6 files load; staged row count = file row count; missing file stops the run with a clear message; load logged in audit_log | F2: None
A3: BR-002 | B3: Maintain source-to-standard code mappings (product, status, collateral, NAICS sector) in a versioned reference table; changes need checker approval | C3: Wrong mappings put loans on the wrong schedule (D09); mappings must be governed like data | D3: Must | E3: Mapping change creates a new version; unapproved mapping is not used; history visible | F3: BR-015
A4: BR-003 | B4: Transform staging into curated tables per mappings M01–M16 | C4: Downstream calculations need clean, typed, standardized data | D4: Must | E4: All 16 mappings implemented; no row dropped silently — every excluded row has an exception record | F4: BR-001, BR-002
A5: BR-004 | B5: Determine each loan's current status as the latest record on or before the as-of date; ties broken by latest load timestamp | C5: Status drives PD and risk weight; the wrong row changes capital | D5: Must | E5: LN1030 = DPD90; LN1015 = CURRENT; exactly one current status per loan | F5: BR-003
A6: BR-005 | B6: Run a configurable library of 15 DQ rules (completeness, validity, uniqueness, accuracy, referential integrity, timeliness), each with a severity | C6: Regulators expect documented, repeatable data controls | D6: Must | E6: All 12 seeded defects detected; each exception stores rule ID, record key, field, value, severity, run ID; rules added via a table row, no code change | F6: BR-003
A7: BR-006 | B7: Block calculation while any Critical exception is open; allow a checker to override or accept a fix with a mandatory reason | C7: Stops bad data reaching capital numbers while keeping the process moving | D7: Must | E7: Calculation button disabled with open criticals; override needs checker ≠ maker and reason text; override logged | F7: BR-005, BR-014
A8: BR-007 | B8: Store stress scenarios and risk parameters as versioned reference data; only ACTIVE, approved versions can be used | C8: Results must be reproducible and parameter changes controlled | D8: Must | E8: 3 scenarios and parameter set v1 loaded; run records versions used; editing ACTIVE creates a new DRAFT | F8: None
A9: BR-008 | B9: Calculate PD, LGD, EAD and 9-quarter stress loss per loan per scenario using Section 9 formulas | C9: Core CCAR credit-loss output | D9: Must | E9: Results match the QA expected-results file within $1 per loan (120 rows); PD, LGD ∈ [0,1]; loss ≤ EAD | F9: BR-004, BR-006, BR-007
A10: BR-009 | B10: Calculate risk weight and RWA per loan, and total RWA including other RWA | C10: CET1 ratio needs a denominator | D10: Must | E10: Loan RWA = $323,637,500; total RWA = $503,637,500 | F10: BR-008
A11: BR-010 | B11: Project 9-quarter PPNR, net income, ending CET1, CET1 ratio and illustrative SCB per scenario | C11: Shows the capital consequence of the scenario, the point of CCAR | D11: Must | E11: Values match Section 9.10 within $1 / 0.01%; each value shows its formula on hover | F11: BR-008, BR-009
A12: BR-011 | B12: Aggregate results by scenario, portfolio, product and rating grade | C12: Reviewers and management look at portfolios, not loans | D12: Must | E12: Totals equal the sum of loan results; drill-down from aggregate to loans works | F12: BR-008
... A20: BR-019 | B20: Publish the same results in a Power BI report | C20: Familiar tool for many bank stakeholders | D20: Could | E20: Power BI reads report tables directly | F20: BR-013

Sheet User Stories
A1: Story | B1: Title | C1: Epic | D1: BR | E1: Priority | F1: Points | G1: Squad | H1: User story | I1: Acceptance criteria | J1: Dependencies | K1: Gherkin scenarios
A2: US-01 | B2: Load source files to staging | C2: E1 Ingestion | D2: BR-001 | E2: Must | F2: 5 | G2: A Data Foundation | H2: As a Data Analyst I want the quarter-end source files loaded into staging with a batch ID so that every number can be traced to a specific source delivery. | I2: 6 files loaded from /landing/<as-of>/; row counts reconciled file vs table; missing or empty file stops the run; load logged. | J2: environment set-up | K2: Scenario: All files present Given the six source files for 2026-06-30 are in the landing folder When the ingestion job runs Then each stg table row count equals its file row count And loansys_balance has 41 rows in staging And one LOAD event per file is written to audit_log Scenario: Missing file Given collsys_collateral.csv is missing When the ingestion job runs Then the run status is FAILED_INGESTION And the message names the missing file
A3: US-02 | B3: Maintain code mappings | C3: E1 Ingestion | D3: BR-002 | E3: Must | F3: 3 | G3: A Data Foundation | H3: As a Business Analyst I want to maintain product, status and collateral mappings in a reference table with approval so that mapping errors are controlled and visible. | I3: mappings editable in UI or CSV upload; change creates DRAFT version; checker approval activates it; history kept. | J3: US-13 (audit) | K3: Scenario: Fixing the CRM mapping Given PRODUCT code CRM maps to CI_TERM in the active mapping When the BA changes the target to CRE_MULTIFAMILY Then a new DRAFT mapping version is created And the active mapping still shows CI_TERM until a checker approves When a different user approves the change Then CRM maps to CRE_MULTIFAMILY and the change is in audit_log with before and after values
A4: US-03 | B4: Transform staging to curated | C4: E2 Transformation | D4: BR-003 | E4: Must | F4: 8 | G4: A Data Foundation | H4: As a Data Engineer I want staging data typed, standardized and loaded into curated tables per the mapping spec so that calculations use clean, consistent data. | I4: mappings M01–M13 implemented; rows that fail a transformation go to exceptions, never silently dropped; duplicate balance rows collapsed with the removed row logged. | J4: US-01, US-02 | K4: Scenario: Unmapped code is not dropped silently Given loan LN1029 has status code XX When the transformation runs Then LN1029 is loaded to curated with status UNMAPPED And a dq_exception is raised for rule DQ-V02 Scenario: Duplicate balance collapsed Given LN1025 has two identical balance rows for 2026-06-30 When the transformation runs Then cur.loan_balance has exactly one row for LN1025
A5: US-04 | B5: Derive current loan status | C5: E2 Transformation | D5: BR-004 | E5: Must | F5: 3 | G5: A Data Foundation | H5: As a Risk Analyst I want each loan's current status to be its latest status on or before the as-of date so that PD and risk weight use the right delinquency state. | I5: See Gherkin scenarios | J5: US-03 | K5: Scenario: Several status changes Given LN1030 has status records 30, 60 and 90 effective 2026-04-20, 2026-05-20 and 2026-06-19 When current status is derived for 2026-06-30 Then LN1030 current status is DPD90 Scenario: Two records on the same day Given LN1015 has status 30 loaded 06:00 and status C loaded 14:30 both effective 2026-06-15 When current status is derived Then LN1015 current status is CURRENT And a warning exception DQ-U02 records the tie
A6: US-05 | B6: Run DQ rule library | C6: E3 Data Quality | D6: BR-005 | E6: Must | F6: 8 | G6: B Quality & Recon | H6: As a Data Analyst I want the 15 DQ rules to run automatically after transformation so that data problems are caught before they reach capital numbers. | I6: rules stored as rows in ctl.dq_rule (ID, dimension, SQL, severity, owner); each failure creates one exception; DQ scorecard shows pass rate by dimension. | J6: US-03, US-04 | K6: Scenario: Seeded defects are detected Given the 2026-06-30 source data with 12 seeded defects When the DQ rules run Then at least one exception exists for each of D01 to D12 And critical exceptions are flagged for D01, D02, D04 to D10 Scenario: A BA adds a new rule without code Given a new row DQ-A04 is inserted into ctl.dq_rule with status ACTIVE When the DQ rules run Then DQ-A04 results appear on the scorecard
A7: US-06 | B7: Review and resolve DQ exceptions | C7: E3 Data Quality | D7: BR-006 | E7: Must | F7: 5 | G7: B Quality & Recon | H7: As a Report Reviewer I want to approve fixes or overrides for critical exceptions so that the run can continue without hiding problems. | I7: See Gherkin scenarios | J7: US-05, US-13 | K7: Scenario: Calculation blocked by open critical exception Given exception D02 (null rating on C0019) is OPEN and critical When the Risk Analyst tries to start the calculation Then the calculation is blocked with the message "1 or more critical exceptions open" Scenario: Override with reason Given analyst1 proposes rating 7 for C0019 with reason "conservative default pending credit review" When reviewer1 approves the override Then the exception status is OVERRIDDEN And audit_log stores old value NULL, new value 7, maker analyst1, checker reviewer1 Scenario: Maker cannot approve own override Given analyst1 proposed the override When analyst1 tries to approve it Then the approval is rejected
A8: US-07 | B8: Manage scenarios and parameters | C8: E4 Calculation | D8: BR-007 | E8: Must | F8: 3 | G8: C Risk & Capital | H8: As a Risk Analyst I want to view, version and activate scenarios and parameters so that each run uses a controlled, reproducible set of assumptions. | I8: See Gherkin scenarios | J8: none | K8: Scenario: Only active scenarios can run Given scenario SEV version 2 is DRAFT and version 1 is ACTIVE When I open scenario selection Then only SEV version 1 can be selected Scenario: Run records versions When I run BASE, MOD and SEV Then calc_run stores scenario versions and parameter version 1
A9: US-08 | B9: Calculate loan-level credit risk | C9: E4 Calculation | D9: BR-008, BR-009 | E9: Must | F9: 8 | G9: C Risk & Capital | H9: As a Risk Analyst I want PD, LGD, EAD, stress loss, risk weight and RWA calculated per loan per scenario so that I can see which loans drive stressed losses. | I9: 120 result rows (40 loans × 3 scenarios); each matches the QA expected file within $1; integrity checks (PD, LGD in [0,1], loss ≤ EAD, one row per loan per scenario) pass. | J9: US-04, US-06, US-07 | K9: Scenario Outline: Worked examples When the calculation runs for <loan> under <scenario> Then EAD is <ead> and LGD is <lgd> and stress loss is <loss> Examples: | loan | scenario | ead | lgd | loss | | LN1012 | BASE | 7125000.00 | 0.4500 | 144281.25 | | LN1012 | SEV | 7125000.00 | 0.4500 | 432843.75 | | LN1019 | SEV | 28750000.00| 0.3238 | 1466325.00 | | LN1030 | MOD | 1975000.00 | 0.4500 | 888750.00 | Scenario: Portfolio RWA When the calculation completes Then total loan RWA is 323637500.00
A10: US-09 | B10: Project PPNR and capital | C10: E4 Calculation | D10: BR-010, BR-011 | E10: Must | F10: 5 | G10: C Risk & Capital | H10: As a Controller I want PPNR, net income, ending CET1 and CET1 ratio projected for each scenario so that I can see whether the bank stays above minimum capital under stress. | I10: values match Section 9.10; aggregates by portfolio, product and rating sum to the total; every figure shows its formula and inputs on hover. | J10: US-08 | K10: Scenario: Severe capital outcome Given starting CET1 60400000 and total RWA 503637500 When the capital projection runs for SEV Then total stress loss is 24180053.76 And ending CET1 ratio is 8.53% And the illustrative SCB is 3.86% Scenario: Scenario ordering When all three scenarios are projected Then SEV loss >= MOD loss >= BASE loss And SEV ending ratio <= MOD ending ratio <= BASE ending ratio
A11: US-10 | B11: Reconcile source, curated and GL | C11: E5 Recon & Reporting | D11: BR-012 | E11: Must | F11: 5 | G11: B Quality & Recon | H11: As a Data Analyst I want automatic count and balance reconciliations with a bridge of every difference so that I can prove the numbers are complete before review. | I11: file → staging → curated count and amount checks; curated vs GL by account; bridge items auto-classified (duplicate, orphan, correction, supplementary); breaks above tolerance need a comment. | J11: US-03, US-06 | K11: Scenario: Balance bridge Given the raw balance file totals 279700000 over 41 rows When reconciliation runs after all fixes Then curated outstanding totals 286600000 over 40 loans And the bridge shows: duplicate -3900000, orphan -2400000, sign correction +4500000, supplementary +8700000 Scenario: Explained GL break Given GL total is 289000000 When curated is reconciled to GL Then a break of 2400000 on GL 141000 is raised And the break cannot be marked EXPLAINED without a comment
A12: US-11 | B12: Generate regulatory-style reports | C12: E5 Recon & Reporting | D12: BR-013, BR-012 | E12: Must | F12: 8 | G12: D Reporting & Governance | H12: As a Data Analyst I want R1 (Y-14Q-style) and R2 (Y-14A-style) generated with edit checks so that I can submit a validated report for review. | I12: fields per Section 11; edit checks E01–E11 run; report reconciliations RR01–RR05 run; export to CSV and Excel equals the on-screen report. | J12: US-09, US-10 | K12: Scenario: Mapping defect caught at report level Given the CRM mapping defect has not been fixed When R1 is generated Then edit check E06 fails for 5 loans in R1-CORP And the report cannot move to IN_REVIEW Scenario: Clean report Given all critical DQ exceptions are resolved When R1 is generated Then R1-CORP has 25 rows and R1-CRE has 15 rows And RR02 passes with utilized total 286600000
A13: US-12 | B13: Maker-checker approval | C13: E6 Governance | D13: BR-014 | E13: Must | F13: 5 | G13: D Reporting & Governance | H13: As a Report Reviewer I want to approve or reject a report with comments, with final Controller sign-off on R2 so that no report is final without independent review. | I13: See Gherkin scenarios | J13: US-11, US-13 | K13: Scenario: Approve Given R1 v1 is IN_REVIEW, prepared by analyst1 When reviewer1 approves it Then R1 v1 status is APPROVED and it is read-only Scenario: Reject and regenerate Given R2 v1 is IN_REVIEW When reviewer1 rejects it with comment "Recheck CRE LGD for LN1017" Then R2 v1 status is REJECTED And regeneration creates R2 v2 in DRAFT Scenario: Segregation of duties Given analyst1 prepared R1 v1 When analyst1 tries to approve R1 v1 Then the action is refused
... A17: US-16 | B17: One-command pipeline run | C17: E7 Demo readiness | D17: BR-018 | E17: Should | F17: 3 | G17: A Data Foundation | H17: As a Scrum team member I want to run ingestion to report with one command so that the demo and regression tests are repeatable. | I17: See Gherkin scenarios | J17: US-01 to US-10 | K17: Scenario: Clean run Given the clean dataset (all fixes applied) When I run run_pipeline.py --asof 2026-06-30 Then the run completes in under 5 minutes with status READY_FOR_REVIEW Scenario: Run stops at DQ gate Given the raw dataset with seeded defects When I run the pipeline Then it stops with status DQ_BLOCKED and lists the open critical exceptions

Sheet Test Scenarios
A1: One row per Gherkin scenario. QA fills the last two columns during each sprint.
A3: Story | B3: Story title | C3: Squad | D3: Scenario | E3: Result (Pass / Fail) | F3: Tested by / date
A4: US-01 | B4: Load source files to staging | C4: A Data Foundation | D4: All files present
A5: US-01 | B5: Load source files to staging | C5: A Data Foundation | D5: Missing file
A6: US-02 | B6: Maintain code mappings | C6: A Data Foundation | D6: Fixing the CRM mapping
A7: US-03 | B7: Transform staging to curated | C7: A Data Foundation | D7: Unmapped code is not dropped silently
A8: US-03 | B8: Transform staging to curated | C8: A Data Foundation | D8: Duplicate balance collapsed
A9: US-04 | B9: Derive current loan status | C9: A Data Foundation | D9: Several status changes
A10: US-04 | B10: Derive current loan status | C10: A Data Foundation | D10: Two records on the same day
A11: US-05 | B11: Run DQ rule library | C11: B Quality & Recon | D11: Seeded defects are detected
A12: US-05 | B12: Run DQ rule library | C12: B Quality & Recon | D12: A BA adds a new rule without code
A13: US-06 | B13: Review and resolve DQ exceptions | C13: B Quality & Recon | D13: Calculation blocked by open critical exception
A14: US-06 | B14: Review and resolve DQ exceptions | C14: B Quality & Recon | D14: Override with reason
A15: US-06 | B15: Review and resolve DQ exceptions | C15: B Quality & Recon | D15: Maker cannot approve own override
... A34: US-16 | B34: One-command pipeline run | C34: A Data Foundation | D34: Run stops at DQ gate

Sheet Tables Overview
A1: Table | B1: Purpose | C1: Primary key | D1: Foreign keys
A2: cur.customer | B2: Obligor (borrower) master | C2: customer_id | D2: —
A3: cur.loan_master | B3: Static loan terms | C3: loan_id | D3: customer_id → customer
A4: cur.loan_balance | B4: Quarter-end balances | C4: loan_id + as_of_date | D4: loan_id → loan_master
A5: cur.loan_status_history | B5: Every status change per loan | C5: status_hist_id | D5: loan_id → loan_master
A6: cur.collateral | B6: Collateral pledged against loans | C6: collateral_id | D6: loan_id → loan_master
A7: ref.stress_scenario | B7: Scenario variables and multipliers | C7: scenario_id + version | D7: —
A8: ref.risk_parameter | B8: Base PD, LGD, CCF, risk weights | C8: param_id | D8: —
A9: calc.calc_result | B9: Loan-level results per scenario | C9: run_id + loan_id + scenario_id | D9: run_id → calc_run; loan_id → loan_master; scenario_id → stress_scenario
A10: rpt.reg_report / rpt.reg_report_line | B10: Report header and lines | C10: report_id / report_id + line_no | D10: run_id → calc_run; report_id → reg_report
A11: ref.code_map | B11: Source code → standard code | C11: source_system + code_type + source_code | D11: —
A12: ctl.calc_run | B12: One row per pipeline run | C12: run_id | D12: —
... A16: ctl.audit_log | B16: Append-only event log | C16: audit_id | D16: run_id → calc_run

Sheet Data Dictionary
A1: Table | B1: Field | C1: Description | D1: Data type | E1: Example
A2: Customer (cur.customer) | B2: customer_id | C2: Unique obligor ID from LOANSYS | D2: VARCHAR(10) | E2: C0007
A3: Customer (cur.customer) | B3: customer_name | C3: Legal name (synthetic) | D3: VARCHAR(100) | E3: Lakeside Precision Tooling LLC
A4: Customer (cur.customer) | B4: naics_code | C4: Industry classification (NAICS) | D4: CHAR(6) | E4: 332710
A5: Customer (cur.customer) | B5: industry_segment | C5: Mapped industry group | D5: VARCHAR(40) | E5: Manufacturing
A6: Customer (cur.customer) | B6: state_code | C6: US state of headquarters | D6: CHAR(2) | E6: OH
A7: Customer (cur.customer) | B7: obligor_rating | C7: Internal risk rating, 1 (best) to 10 (default) | D7: SMALLINT | E7: 5
A8: Customer (cur.customer) | B8: customer_since | C8: Relationship start date | D8: DATE | E8: 2014-03-01
A9: Loan Master (cur.loan_master) | B9: loan_id | C9: Facility ID | D9: VARCHAR(10) | E9: LN1012
A10: Loan Master (cur.loan_master) | B10: customer_id | C10: Borrower | D10: VARCHAR(10) | E10: C0007
A11: Loan Master (cur.loan_master) | B11: src_product_code | C11: Product code as received | D11: VARCHAR(10) | E11: CIT
A12: Loan Master (cur.loan_master) | B12: product_code | C12: Standard product (after mapping) | D12: VARCHAR(20) | E12: CI_TERM
... A75: Regulatory Report (rpt.reg_report + rpt.reg_report_line) | B75: lineage_ref | C75: Source table.field the value came from | D75: VARCHAR(100) | E75: cur.loan_balance.outstanding_bal

Sheet Mapping (M01-M16)
A1: # | B1: Source table | C1: Source field | D1: Business rule | E1: Transformation | F1: Target table | G1: Target field
A2: M01 | B2: loansys_customer | C2: customer_id | D2: Must be unique and not null | E2: TRIM, UPPER | F2: cur.customer | G2: customer_id
A3: M02 | B3: loansys_customer | C3: obligor_rating | D3: Integer 1–10; null is a critical exception | E3: CAST to SMALLINT; approved override if null | F3: cur.customer | G3: obligor_rating
A4: M03 | B4: loansys_customer | C4: naics_code | D4: 6 digits; null allowed with warning | E4: First 2 digits → sector via ref.code_map (NAICS2); null → UNKNOWN | F4: cur.customer | G4: industry_segment
A5: M04 | B5: loansys_loan | C5: product_code | D5: Every code must exist in the mapping | E5: Lookup ref.code_map (PRODUCT) | F5: cur.loan_master | G5: product_code
A6: M05 | B6: loansys_loan | C6: product_code | D6: Derived | E6: CASE WHEN product_code LIKE 'CRE%' THEN 'CRE' ELSE 'CI' END | F6: cur.loan_master | G6: portfolio
A7: M06 | B7: loansys_loan | C7: commitment_amt | D7: > 0 | E7: CAST NUMERIC(18,2) | F7: cur.loan_master | G7: commitment_amt
A8: M07 | B8: loansys_loan | C8: interest_rate | D8: 0 < rate < 0.25; not null | E8: CAST NUMERIC(7,5) | F8: cur.loan_master | G8: interest_rate
A9: M08 | B9: loansys_loan | C9: hvcre_flag | D9: Y or N; CRE products only | E9: UPPER; default N | F9: cur.loan_master | G9: hvcre_flag
A10: M09 | B10: loansys_balance | C10: outstanding_bal | D10: One row per loan per as-of date; ≥ 0; ≤ commitment | E10: CAST; de-duplicate on (loan_id, as_of_date) | F10: cur.loan_balance | G10: outstanding_bal
A11: M10 | B11: loansys_balance + loansys_loan | C11: outstanding_bal, commitment_amt | D11: Derived | E11: GREATEST(commitment_amt - outstanding_bal, 0) | F11: cur.loan_balance | G11: undrawn_amt
A12: M11 | B12: loansys_status | C12: status_code, effective_date, load_ts | D12: Latest effective_date ≤ as-of; tie → latest load_ts | E12: ROW_NUMBER() window; lookup ref.code_map (STATUS) | F12: cur.loan_master (view v_loan_current_status) | G12: current_status
... A17: M16 | B17: calc.calc_result | C17: stress_loss | D17: Sum by scenario | E17: SUM(stress_loss) GROUP BY scenario_id | F17: rpt.reg_report_line | G17: Y-14A-style credit losses

Sheet Code Map
A1: code_type | B1: source_code | C1: target_code
A2: PRODUCT | B2: CIT | C2: CI_TERM
A3: PRODUCT | B3: CIR | C3: CI_REVOLVER
A4: PRODUCT | B4: CRO | C4: CRE_OFFICE
A5: PRODUCT | B5: CRM | C5: CI_TERM ← seeded defect D09; correct value CRE_MULTIFAMILY
A6: PRODUCT | B6: CRR | C6: CRE_RETAIL
A7: PRODUCT | B7: CRI | C7: CRE_INDUSTRIAL
A8: STATUS | B8: C / 30 / 60 / 90 / NA / PO | C8: CURRENT / DPD30 / DPD60 / DPD90 / NONACCRUAL / PAIDOFF
A9: COLLATERAL | B9: OFF / MFR / RTL / IND / EQP / ARI | C9: CRE_OFFICE / CRE_MF / CRE_RETAIL / CRE_IND / EQUIPMENT / AR_INV

Sheet Seeded Defects
A1: # | B1: Defect type | C1: Where | D1: What is wrong | E1: How to detect | F1: How to resolve (POC decision) | G1: Detected? (Y/N) | H1: Resolved? (Y/N)
A2: D01 | B2: NULL value (critical) | C2: LN1018 interest_rate | D2: Rate missing | E2: Completeness rule: interest_rate IS NULL | F2: Request correction from LOANSYS; corrected file gives 0.0695
A3: D02 | B3: NULL value (critical) | C3: C0019 obligor_rating (drives LN1021) | D3: No rating, so no PD | E3: Completeness rule on rating | F3: Checker-approved override to rating 7 (conservative), logged in audit
A4: D03 | B4: NULL value (warning) | C4: C0014 naics_code | D4: Industry missing | E4: Completeness rule, warning severity | F4: Flag only; industry shown as UNKNOWN in the report
A5: D04 | B5: Duplicate record | C5: LN1025 balance row appears twice | D5: Balance double-counted (+$3.9M) | E5: Uniqueness rule: GROUP BY loan_id, as_of_date HAVING COUNT(*) > 1 | F5: Keep one row; log removed row
A6: D05 | B6: Missing record | C6: LN1033 has no balance row | D6: Loan silently disappears from results | E6: Anti-join loan_master → loan_balance | F6: Supplementary file from LOANSYS gives $8.7M
A7: D06 | B7: Missing parent (orphan) | C7: LN1041 in balance file, not in loan master | D7: $2.4M balance with no loan terms | E7: Anti-join loan_balance → loan_master | F7: Excluded from run; recorded as explained GL break (loan booked after master extract cut-off)
A8: D07 | B8: Referential integrity | C8: LN1038 points to customer C0026, not in customer file | D8: No rating, no industry | E8: FK check loan_master → customer | F8: Supplementary customer record added (rating 6)
A9: D08 | B9: Invalid status | C9: LN1029 status code XX | D9: Code not in mapping table | E9: Validity rule: code not in ref.code_map | F9: Source confirms 60 days past due (matches days_past_due = 64)
A10: D09 | B10: Incorrect mapping | C10: ref.code_map: PRODUCT CRM → CI_TERM | D10: 5 multifamily loans ($67.55M) land in the C&I extract | E10: Cross-field rule: C&I product with CRE collateral | F10: Fix mapping to CRE_MULTIFAMILY (mapping change goes through approval)
A11: D10 | B11: Incorrect balance | C11: LN1021 balance is −$2,250,000; LN1010 balance $4.35M > commitment $4.0M | D11: Negative balance; over-limit | E11: Accuracy rules: balance < 0; balance > commitment | F11: LN1021: sign error, corrected to +$2.25M. LN1010: commitment amendment to $4.5M not loaded; master corrected
A12: D11 | B12: Multiple status records | C12: LN1030 has 3 records (30 → 60 → 90); LN1015 has 2 records with the same effective date | D12: Wrong status if the wrong row is chosen | E12: Latest-status query; tie check on effective date | F12: LN1030 = DPD90 (defaulted). LN1015: latest load_ts wins → CURRENT (cured)
A13: D12 | B13: Stale data (warning) | C13: CL2006 appraisal dated 2023-02-10 (> 24 months) | D13: Collateral value may be overstated | E13: Timeliness rule on valuation_date | F13: Warning; flagged for re-appraisal, value used as-is

Sheet DQ Dimensions
A1: Dimension | B1: Question it answers | C1: POC controls
A2: Completeness | B2: Is everything there? | C2: NULL checks on key fields; every loan has a balance; file counts match
A3: Accuracy | B3: Are values right? | C3: Balance ≥ 0 and ≤ commitment; cross-field product vs collateral; GL tie-out
A4: Validity | B4: Are values allowed? | C4: Codes exist in mapping; rating 1–10; dates logical
A5: Uniqueness | B5: Is anything counted twice? | C5: One balance per loan per date; one status per loan per date
A6: Referential integrity | B6: Do links hold? | C6: Balance → loan; loan → customer; collateral → loan
A7: Timeliness | B7: Is data current? | C7: Collateral appraisal ≤ 24 months
A8: Source-to-target reconciliation | B8: Did anything get lost or added between layers? | C8: Counts and sums: file → staging → curated → report; curated → GL
A9: Calculation validation | B9: Are the numbers computed correctly? | C9: Independent recompute; QA oracle; range checks; scenario ordering
A10: Exception handling | B10: Are problems resolved under control? | C10: Exception workflow with maker-checker and reasons
A11: Audit trail | B11: Can we prove it later? | C11: Append-only audit_log (Section 18)

Sheet DQ Rules
A1: Rule | B1: Dimension | C1: Rule logic | D1: Severity | E1: Expected exceptions (raw data) | F1: Defect | G1: Pass on clean data? (Y/N)
A2: DQ-C01 | B2: Completeness | C2: loan.interest_rate IS NOT NULL | D2: Critical | E2: 1 (LN1018) | F2: D01
A3: DQ-C02 | B3: Completeness | C3: customer.obligor_rating IS NOT NULL | D3: Critical | E3: 1 (C0019) | F3: D02
A4: DQ-C03 | B4: Completeness | C4: customer.naics_code IS NOT NULL | D4: Warning | E4: 1 (C0014) | F4: D03
A5: DQ-C04 | B5: Completeness | C5: Every loan has a balance row for the as-of date | D5: Critical | E5: 1 (LN1033) | F5: D05
A6: DQ-V01 | B6: Validity | C6: obligor_rating BETWEEN 1 AND 10 | D6: Critical | E6: 0 | F6: —
A7: DQ-V02 | B7: Validity | C7: status_code exists in code_map (STATUS) | D7: Critical | E7: 1 (LN1029) | F7: D08
A8: DQ-V03 | B8: Validity | C8: product_code exists in code_map (PRODUCT) | D8: Critical | E8: 0 | F8: —
A9: DQ-U01 | B9: Uniqueness | C9: One balance row per loan_id + as_of_date | D9: Critical | E9: 1 (LN1025) | F9: D04
A10: DQ-U02 | B10: Uniqueness | C10: One status row per loan_id + effective_date | D10: Warning | E10: 1 (LN1015) | F10: D11
A11: DQ-A01 | B11: Accuracy | C11: outstanding_bal ≥ 0 | D11: Critical | E11: 1 (LN1021) | F11: D10
A12: DQ-A02 | B12: Accuracy | C12: outstanding_bal ≤ commitment_amt | D12: Critical | E12: 1 (LN1010) | F12: D10
A13: DQ-A03 | B13: Accuracy | C13: C&I product must not have CRE collateral | D13: Critical | E13: 5 (LN1007, LN1014, LN1024, LN1036, LN1040) | F13: D09
... A16: DQ-T01 | B16: Timeliness | C16: valuation_date ≥ as-of date − 24 months | D16: Warning | E16: 1 (CL2006) | F16: D12

Sheet DQ Exception Workflow
A1: Status | B1: Meaning | C1: Who | D1: Next
A2: OPEN | B2: Raised by a rule run | C2: System | D2: FIX_PROPOSED, OVERRIDE_PROPOSED, ACCEPTED (warnings only)
A3: FIX_PROPOSED | B3: Corrected source file or record supplied | C3: Data Analyst | D3: RESOLVED once the rerun passes
A4: OVERRIDE_PROPOSED | B4: Value changed in curated with a reason | C4: Data Analyst (maker) | D4: OVERRIDDEN after checker approval, or back to OPEN
A5: OVERRIDDEN | B5: Override approved | C5: Report Reviewer (checker ≠ maker) | D5: Closed; before/after in audit
A6: ACCEPTED | B6: Warning acknowledged with comment | C6: Report Reviewer | D6: Closed
A7: RESOLVED | B7: Rule passes on rerun | C7: System | D7: Closed

Sheet Recon Checks
A1: ID | B1: Reconciliation | C1: Expected result on sample data | D1: Tolerance | E1: Outcome
A2: RC-01 | B2: File trailer / row count vs staging count (each file) | C2: Match for all 6 files (balance file: 41 = 41) | D2: 0 rows | E2: Pass
A3: RC-02 | B3: Balance amount: file vs staging | C3: $279,700,000 = $279,700,000 | D3: $0 | E3: Pass
A4: RC-03 | B4: Staging → curated balance count | C4: 41 → 40 | D4: Every difference itemized | E4: Explained (bridge below)
A5: RC-04 | B5: Staging → curated balance amount | C5: $279.7M → $286.6M | D5: Every difference itemized | E5: Explained (bridge below)
A6: RC-05 | B6: Curated vs GL 141000 (C&I) | C6: $83,550,000 vs $85,950,000 | D6: $1,000 or 0.01% | E6: Break $2.4M → explained: LN1041 not in loan master
A7: RC-06 | B7: Curated vs GL 142000 (CRE) | C7: $203,050,000 vs $203,050,000 | D7: $1,000 or 0.01% | E7: Pass
A8: RC-07 | B8: Curated → R1 report (count, utilized, committed) | C8: 40 / $286.6M | D8: $1 | E8: Pass (RR01–RR03)
A9: RC-08 | B9: calc_result → R2 losses by scenario | C9: $6.52M / $11.86M / $24.18M | D9: $1 | E9: Pass (RR04)

Sheet Recon Bridge
A1: Step | B1: Rows | C1: Amount | D1: Reason
A2: Source balance file | B2: 41 | C2: $279,700,000 | D2: As received
A3: Remove duplicate LN1025 | B3: −1 | C3: −$3,900,000 | D3: D04
A4: Exclude orphan LN1041 | B4: −1 | C4: −$2,400,000 | D4: D06 (stays in GL break RC-05)
A5: Correct LN1021 sign (−$2.25M → +$2.25M) | B5: 0 | C5: +$4,500,000 | D5: D10
A6: Add supplementary LN1033 | B6: +1 | C6: +$8,700,000 | D6: D05
A7: Curated balance | B7: 40 | C7: $286,600,000 | D7: Ties to R1
A8: Add LN1041 (explained break) | B8: +1 | C8: +$2,400,000 | D8: Booked after master cut-off
A9: GL total (141000 + 142000) | B9: — | C9: $289,000,000 | D9: Ties

Sheet Controls
A1: Control | B1: Description | C1: Type | D1: Step | E1: Owner | F1: Evidence
A2: CTL-01 | B2: File presence, as-of date and row-count check on ingestion | C2: Preventive | D2: Ingest | E2: Data Engineer | F2: ctl.file_control, audit LOAD events
A3: CTL-02 | B3: Mapping changes need checker approval and are versioned | C3: Preventive | D3: Map | E3: BA / Reviewer | F3: ref.code_map versions, audit MAPPING_CHANGE
A4: CTL-03 | B4: 15 DQ rules run every time; results stored | C4: Detective | D4: DQ | E4: Data Analyst | F4: dq_exception, scorecard
A5: CTL-04 | B5: Calculation blocked while critical exceptions are open | C5: Preventive | D5: DQ → Calc | E5: System | F5: calc_run status DQ_BLOCKED
A6: CTL-05 | B6: Overrides need a reason and a different approver | C6: Preventive | D6: DQ | E6: Reviewer | F6: audit OVERRIDE with before/after
A7: CTL-06 | B7: Only ACTIVE scenario and parameter versions usable | C7: Preventive | D7: Scenario | E7: Risk Analyst lead | F7: calc_run.scenario_versions
A8: CTL-07 | B8: Calculation integrity checks (ranges, completeness, ordering) | C8: Detective | D8: Calc | E8: System / QA | F8: calc_run check results
A9: CTL-08 | B9: Source → curated → report → GL reconciliation with commented breaks | C9: Detective | D9: Recon | E9: Data Analyst | F9: recon_result, bridge
A10: CTL-09 | B10: Report edit checks E01–E11 must pass before review | C10: Preventive | D10: Report | E10: System | F10: report check results
A11: CTL-10 | B11: Maker-checker approval; Controller sign-off and attestation on R2 | C11: Preventive | D11: Approve | E11: Reviewer, Controller | F11: reg_report status history
A12: CTL-11 | B12: Approved reports locked; changes create new versions; exports hashed | C12: Preventive | D12: Approve | E12: System | F12: report versions, SHA-256 in audit EXPORT
A13: CTL-12 | B13: Audit log append-only (DB trigger rejects UPDATE/DELETE) | C13: Preventive | D13: All | E13: Data Engineer | F13: Trigger definition, test evidence

Sheet Scenarios
A1: Variable | B1: Baseline (BASE) | C1: Moderate Stress (MOD) | D1: Severe Stress (SEV) | E1: Used in
A2: Peak unemployment rate | B2: 4.3% | C2: 7.0% | D2: 10.0% | E2: Narrative only
A3: Real GDP, peak to trough | B3: +1.8% (growth) | C3: −1.5% | D3: −4.0% | E3: Narrative only
A4: CRE price change | B4: 0% | C4: −20% | D4: −40% | E4: LGD (CRE collateral)
A5: BBB corporate spread, peak | B5: 1.5 pts | C5: 3.0 pts | D5: 5.0 pts | E5: Narrative only
A6: PD multiplier, C&I | B6: 1.0× | C6: 1.8× | D6: 3.0× | E6: PD
A7: PD multiplier, CRE | B7: 1.0× | C7: 2.0× | D7: 3.5× | E7: PD
A8: Haircut on equipment / receivables collateral | B8: 0% | C8: 15% | D8: 30% | E8: LGD (non-CRE collateral)
A9: PPNR factor | B9: 1.00 | C9: 0.85 | D9: 0.60 | E9: PPNR

Sheet Parameters
A1: Parameter | B1: Value | C1: Label
A2: Base annual PD by rating 1–10 | B2: 0.05%, 0.10%, 0.30%, 0.80%, 2.00%, 4.00%, 8.00%, 15.00%, 30.00%, 100% | C2: [POC]
A3: PD for DPD30 / DPD60 loans | B3: max(rating PD, 15%) | C3: [POC]
A4: PD for DPD90 / NONACCRUAL loans | B4: 100% (treated as defaulted) | C4: [POC], consistent with the common 90-days-past-due default definition
A5: Horizon factor (annual → 9-quarter) | B5: 2.25 | C5: [POC] linear; a model would use 1 − (1 − PD)^2.25 or quarterly PDs
A6: Credit conversion factor (CCF) | B6: 50% on all undrawn amounts | C6: [POC]; [CCAR] US standardized approach uses 50% for commitments over one year, 20% for one year or less
A7: Unsecured LGD | B7: 45% | C7: [POC]; same figure as the Basel foundation-IRB senior unsecured LGD
A8: LGD floor / cap for secured loans | B8: 10% / 45% | C8: [POC]
A9: Recovery (liquidation) cost | B9: 10% of stressed collateral value | C9: [POC]
A10: Risk weight: C&I, non-HVCRE CRE | B10: 100% | C10: [CCAR] US standardized approach, simplified
A11: Risk weight: HVCRE, or 90+ DPD / nonaccrual | B11: 150% | C11: [CCAR] US standardized approach, simplified
A12: Tax rate | B12: 21% | C12: [ASSUMPTION] US federal statutory rate; no state tax or deferred tax

Sheet Worked Examples
A1: Loan | B1: Scenario | C1: Outstanding | D1: Undrawn | E1: EAD | F1: PD base | G1: PD 9Q | H1: LGD | I1: Stress loss
A2: LN1012 C&I term, rating 5, unsecured | B2: Baseline | C2: $6,250,000 | D2: $1,750,000 | E2: $7,125,000 | F2: 2.00% | G2: 4.50% | H2: 45.00% | I2: $144,281.25
A3: LN1012 | B3: Severe | C3: $6,250,000 | D3: $1,750,000 | E3: $7,125,000 | F3: 2.00% | G3: 13.50% | H3: 45.00% | I3: $432,843.75
A4: LN1019 CRE office, rating 5, $36M collateral | B4: Severe | C4: $27,500,000 | D4: $2,500,000 | E4: $28,750,000 | F4: 2.00% | G4: 15.75% | H4: 32.38% | I4: $1,466,325.00
A5: LN1030 C&I revolver, DPD90 (defaulted) | B5: Any | C5: $1,950,000 | D5: $50,000 | E5: $1,975,000 | F5: 100% | G5: 100% | H5: 45.00% (capped) | I5: $888,750.00

Sheet Report R1 Fields
A1: Field | B1: Source / calculation | C1: Applies to
A2: Reporting date | B2: calc_run.as_of_date | C2: Both
A3: Loan ID, Obligor ID, Obligor name | B3: cur.loan_master, cur.customer | C3: Both
A4: Industry (NAICS) and state | B4: cur.customer | C4: Both
A5: Obligor internal rating | B5: cur.customer.obligor_rating | C5: Both
A6: Facility type | B6: cur.loan_master.product_code | C6: Both
A7: Origination date, maturity date | B7: cur.loan_master | C7: Both
A8: Committed exposure | B8: cur.loan_master.commitment_amt | C8: Both
A9: Utilized exposure | B9: cur.loan_balance.outstanding_bal | C9: Both
A10: Interest rate, rate type | B10: cur.loan_master | C10: Both
A11: Days past due, non-accrual flag | B11: cur.loan_balance.days_past_due; current_status = NONACCRUAL | C11: Both
A12: Collateral type, collateral value | B12: cur.collateral (sum per loan) | C12: Both (null if unsecured)
... A17: Stress loss by scenario [POC-added] | B17: calc.calc_result | C17: Both

Sheet Report R2 Lines
A1: Line | B1: Description | C1: Calculation
A2: A1 | B2: Starting CET1 | C2: Input (bank-level)
A3: A2 | B3: PPNR, 9 quarters | C3: Section 9.7
A4: A3 | B4: Credit losses — C&I | C4: SUM(stress_loss) where portfolio = CI
A5: A4 | B5: Credit losses — CRE | C5: SUM(stress_loss) where portfolio = CRE
A6: A5 | B6: Total provisions | C6: A3 + A4
A7: A6 | B7: Pre-tax net income | C7: A2 − A5
A8: A7 | B8: Taxes | C8: A6 × 21%
A9: A8 | B9: Net income | C9: A6 − A7
A10: A9 | B10: Common dividends | C10: Input: $0.5M × 9
A11: A10 | B11: Ending CET1 | C11: A1 + A8 − A9
A12: A11 | B12: Total RWA | C12: Loan RWA + other RWA
... A14: A13 | B14: Illustrative SCB [POC] | C14: max(2.5%, start ratio − end ratio + 4 quarters of dividends / A11)

Sheet Edit Checks
A1: ID | B1: Rule | C1: Severity | D1: Result
A2: E01 | B2: Utilized exposure ≤ committed exposure | C2: Error
A3: E02 | B3: Maturity date > origination date | C3: Error
A4: E03 | B4: Internal rating between 1 and 10 | C4: Error
A5: E04 | B5: R1-CRE rows must have property type and collateral value | C5: Error
A6: E05 | B6: Loan ID is unique within an extract | C6: Error
A7: E06 | B7: R1-CORP contains no CRE product; R1-CRE contains no C&I product | C7: Error
A8: E07 | B8: LTV between 0% and 150% | C8: Warning
A9: E08 | B9: Non-accrual = Y implies internal rating ≥ 7 | C9: Warning
A10: E09 | B10: R2: A10 = A1 + A8 − A9 (tolerance $1) | C10: Error
A11: E10 | B11: R2: Severe losses ≥ Moderate ≥ Baseline | C11: Error
A12: E11 | B12: R2: CET1 ratio recomputes from A10 / A11 within 0.01% | C12: Error

Sheet Report Recon Rules
A1: ID | B1: Reconciliation | C1: Tolerance
A2: RR01 | B2: R1 row count (CORP + CRE) = curated loan count (40) | C2: 0
A3: RR02 | B3: R1 utilized total = curated outstanding total ($286.6M) | C3: $1
A4: RR03 | B4: R1 committed total = curated commitment total | C4: $1
A5: RR04 | B5: R2 losses (A5) = SUM of R1 loss column for that scenario = SUM(calc_result) | C5: $1
A6: RR05 | B6: R1 utilized by portfolio = GL 141000 / 142000, less explained items | C6: $1,000 or 0.01%

Sheet Data - Customer
A1: Raw source file loansys_customer.csv as received (contains seeded defects). Also in data/landing/2026-06-30/.
A3: customer_id | B3: customer_name | C3: naics_code | D3: state_code | E3: obligor_rating | F3: customer_since
A4: C0001 | B4: Blue Ridge Logistics Inc | C4: 484121 | D4: VA | E4: 4 | F4: 2012-04-02
A5: C0002 | B5: Canyon Foods Distribution LLC | C5: 424410 | D5: AZ | E5: 5 | F5: 2015-09-14
A6: C0003 | B6: Harborview Office Partners LP | C6: 531120 | D6: MA | E6: 4 | F6: 2016-01-20
A7: C0004 | B7: Prairie Ag Equipment Co | C7: 423820 | D7: KS | E7: 6 | F7: 2011-06-30
A8: C0005 | B8: Summit Medical Devices Inc | C8: 339112 | D8: MN | E8: 3 | F8: 2018-03-05
A9: C0006 | B9: Riverbend Apartments LLC | C9: 531110 | D9: TX | E9: 4 | F9: 2017-07-11
A10: C0007 | B10: Lakeside Precision Tooling LLC | C10: 332710 | D10: OH | E10: 5 | F10: 2014-03-01
A11: C0008 | B11: Golden Gate Retail Center LP | C11: 531120 | D11: CA | E11: 6 | F11: 2013-10-22
A12: C0009 | B12: Keystone Building Supply Inc | C12: 444110 | D12: PA | E12: 5 | F12: 2019-02-18
A13: C0010 | B13: Metro Industrial Park LLC | C13: 531130 | D13: IL | E13: 3 | F13: 2016-08-09
A14: C0011 | B14: Coastal Seafood Processors Inc | C14: 311710 | D14: ME | E14: 7 | F14: 2010-05-17
A15: C0012 | B15: Pinecrest Senior Living LLC | C15: 531110 | D15: NC | E15: 5 | F15: 2020-01-06
A16: C0013 | B16: Ironclad Security Services Inc | C16: 561612 | D16: GA | E16: 4 | F16: 2018-11-13
A17: C0014 | B17: Northstar Software Solutions Inc | D17: WA | E17: 3 | F17: 2021-04-26
A18: C0015 | B18: Desert Sun Hospitality Group LLC | C18: 721110 | D18: NV | E18: 7 | F18: 2015-12-01
A19: C0016 | B19: Great Lakes Plastics Corp | C19: 326199 | D19: MI | E19: 6 | F19: 2012-09-24
A20: C0017 | B20: Midtown Office Tower LLC | C20: 531120 | D20: NY | E20: 5 | F20: 2014-06-16
A21: C0018 | B21: Sunbelt Distribution Center LP | C21: 531130 | D21: FL | E21: 4 | F21: 2019-05-07
A22: C0019 | B22: Heritage Furniture Makers Inc | C22: 337122 | D22: NC | F22: 2011-02-14
A23: C0020 | B23: Bayou Energy Services LLC | C23: 213112 | D23: LA | E23: 8 | F23: 2013-08-19
A24: C0021 | B24: Oakwood Garden Apartments LP | C24: 531110 | D24: GA | E24: 4 | F24: 2018-10-03
A25: C0022 | B25: Frontier Trucking Co | C25: 484121 | D25: NE | E25: 6 | F25: 2017-03-27
A26: C0023 | B26: Crescent Plaza Shopping Center LLC | C26: 531120 | D26: LA | E26: 7 | F26: 2012-12-10
A27: C0024 | B27: Evergreen Pharma Packaging Inc | C27: 325412 | D27: NJ | E27: 3 | F27: 2020-07-15
A28: C0025 | B28: Silverline Auto Parts Inc | C28: 441310 | D28: TN | E28: 5 | F28: 2016-05-23

Sheet Data - Loan
A1: Raw source file loansys_loan.csv as received (contains seeded defects). Also in data/landing/2026-06-30/.
A3: loan_id | B3: customer_id | C3: product_code | D3: orig_date | E3: maturity_date | F3: commitment_amt | G3: interest_rate | H3: rate_type | I3: hvcre_flag
A4: LN1001 | B4: C0001 | C4: CIT | D4: 2021-03-15 | E4: 2028-03-15 | F4: 6000000 | G4: 0.0685 | H4: FLOAT | I4: N
A5: LN1002 | B5: C0001 | C5: CIR | D5: 2023-01-10 | E5: 2027-01-10 | F5: 4000000 | G5: 0.074 | H5: FLOAT | I5: N
A6: LN1003 | B6: C0002 | C6: CIR | D6: 2022-06-01 | E6: 2027-06-01 | F6: 5000000 | G6: 0.076 | H6: FLOAT | I6: N
A7: LN1004 | B7: C0003 | C7: CRO | D7: 2019-09-30 | E7: 2029-09-30 | F7: 18000000 | G7: 0.0525 | H7: FIXED | I7: N
A8: LN1005 | B8: C0004 | C8: CIT | D8: 2020-11-20 | E8: 2027-11-20 | F8: 3500000 | G8: 0.071 | H8: FIXED | I8: N
A9: LN1006 | B9: C0005 | C9: CIR | D9: 2024-02-12 | E9: 2029-02-12 | F9: 7500000 | G9: 0.069 | H9: FLOAT | I9: N
A10: LN1007 | B10: C0006 | C10: CRM | D10: 2018-05-01 | E10: 2028-05-01 | F10: 22000000 | G10: 0.0475 | H10: FIXED | I10: N
A11: LN1008 | B11: C0007 | C11: CIR | D11: 2021-08-18 | E11: 2026-12-18 | F11: 3000000 | G11: 0.0775 | H11: FLOAT | I11: N
A12: LN1009 | B12: C0008 | C12: CRR | D12: 2017-04-11 | E12: 2027-04-11 | F12: 15000000 | G12: 0.056 | H12: FIXED | I12: N
A13: LN1010 | B13: C0009 | C13: CIR | D13: 2022-10-05 | E13: 2027-10-05 | F13: 4000000 | G13: 0.075 | H13: FLOAT | I13: N
A14: LN1011 | B14: C0010 | C14: CRI | D14: 2020-02-28 | E14: 2030-02-28 | F14: 20000000 | G14: 0.051 | H14: FIXED | I14: N
A15: LN1012 | B15: C0007 | C15: CIT | D15: 2022-05-16 | E15: 2029-05-16 | F15: 8000000 | G15: 0.0725 | H15: FLOAT | I15: N
... A20: LN1017 | B20: C0015 | C20: CRR | D20: 2016-03-18 | E20: 2026-09-18 | F20: 12000000 | G20: 0.061 | H20: FIXED | I20: N
A21: LN1018 | B21: C0016 | C21: CIT | D21: 2020-09-09 | E21: 2027-09-09 | F21: 5500000 | H21: FIXED | I21: N
A22: LN1019 | B22: C0017 | C22: CRO | D22: 2018-11-01 | E22: 2028-11-01 | F22: 30000000 | G22: 0.049 | H22: FIXED | I22: N
A23: LN1020 | B23: C0018 | C23: CRI | D23: 2021-06-14 | E23: 2031-06-14 | F23: 14000000 | G23: 0.053 | H23: FIXED | I23: N
A24: LN1021 | B24: C0019 | C24: CIT | D24: 2019-01-25 | E24: 2027-01-25 | F24: 4500000 | G24: 0.07 | H24: FIXED | I24: N
A25: LN1022 | B25: C0020 | C25: CIR | D25: 2022-03-30 | E25: 2027-03-30 | F25: 6000000 | G25: 0.085 | H25: FLOAT | I25: N
A26: LN1023 | B26: C0017 | C26: CRO | D26: 2025-01-15 | E26: 2028-01-15 | F26: 10000000 | G26: 0.079 | H26: FLOAT | I26: Y
A27: LN1024 | B27: C0021 | C27: CRM | D27: 2019-08-20 | E27: 2029-08-20 | F27: 12500000 | G27: 0.046 | H27: FIXED | I27: N
A28: LN1025 | B28: C0022 | C28: CIT | D28: 2021-10-12 | E28: 2028-10-12 | F28: 5000000 | G28: 0.0715 | H28: FIXED | I28: N
A29: LN1026 | B29: C0023 | C29: CRR | D29: 2015-07-07 | E29: 2027-07-07 | F29: 9500000 | G29: 0.059 | H29: FIXED | I29: N
A30: LN1027 | B30: C0024 | C30: CIR | D30: 2023-09-19 | E30: 2028-09-19 | F30: 6500000 | G30: 0.068 | H30: FLOAT | I30: N
A31: LN1028 | B31: C0025 | C31: CIT | D31: 2020-04-01 | E31: 2027-04-01 | F31: 3800000 | G31: 0.0705 | H31: FIXED | I31: N
A32: LN1029 | B32: C0002 | C32: CIT | D32: 2021-12-01 | E32: 2028-12-01 | F32: 4200000 | G32: 0.072 | H32: FIXED | I32: N
A33: LN1030 | B33: C0011 | C33: CIR | D33: 2022-07-15 | E33: 2027-07-15 | F33: 2000000 | G33: 0.083 | H33: FLOAT | I33: N
... A43: LN1040 | B43: C0021 | C43: CRM | D43: 2025-04-30 | E43: 2035-04-30 | F43: 8500000 | G43: 0.063 | H43: FIXED | I43: N

Sheet Data - Balance
A1: Raw source file loansys_balance.csv as received (contains seeded defects). Also in data/landing/2026-06-30/.
A3: loan_id | B3: as_of_date | C3: outstanding_bal | D3: days_past_due | E3: gl_account
A4: LN1001 | B4: 2026-06-30 | C4: 4200000 | D4: 0 | E4: 141000
A5: LN1002 | B5: 2026-06-30 | C5: 2600000 | D5: 0 | E5: 141000
A6: LN1003 | B6: 2026-06-30 | C6: 3100000 | D6: 0 | E6: 141000
A7: LN1004 | B7: 2026-06-30 | C7: 16200000 | D7: 0 | E7: 142000
A8: LN1005 | B8: 2026-06-30 | C8: 2150000 | D8: 0 | E8: 141000
A9: LN1006 | B9: 2026-06-30 | C9: 3900000 | D9: 0 | E9: 141000
A10: LN1007 | B10: 2026-06-30 | C10: 19800000 | D10: 0 | E10: 142000
A11: LN1008 | B11: 2026-06-30 | C11: 2750000 | D11: 0 | E11: 141000
A12: LN1009 | B12: 2026-06-30 | C12: 13100000 | D12: 0 | E12: 142000
A13: LN1010 | B13: 2026-06-30 | C13: 4350000 | D13: 0 | E13: 141000
A14: LN1011 | B14: 2026-06-30 | C14: 18300000 | D14: 0 | E14: 142000
A15: LN1012 | B15: 2026-06-30 | C15: 6250000 | D15: 0 | E15: 141000
... A44: LN1041 | B44: 2026-06-30 | C44: 2400000 | D44: 0 | E44: 141000

Sheet Data - Status
A1: Raw source file loansys_status.csv as received (contains seeded defects). Also in data/landing/2026-06-30/.
A3: status_hist_id | B3: loan_id | C3: status_code | D3: effective_date | E3: load_ts
A4: 50001 | B4: LN1001 | C4: C | D4: 2021-03-15 | E4: 2021-03-15 06:00:00
A5: 50002 | B5: LN1002 | C5: C | D5: 2023-01-10 | E5: 2023-01-10 06:00:00
A6: 50003 | B6: LN1003 | C6: C | D6: 2022-06-01 | E6: 2022-06-01 06:00:00
A7: 50004 | B7: LN1004 | C7: C | D7: 2019-09-30 | E7: 2019-09-30 06:00:00
A8: 50005 | B8: LN1005 | C8: C | D8: 2020-11-20 | E8: 2020-11-20 06:00:00
A9: 50006 | B9: LN1006 | C9: C | D9: 2024-02-12 | E9: 2024-02-12 06:00:00
A10: 50007 | B10: LN1007 | C10: C | D10: 2018-05-01 | E10: 2018-05-01 06:00:00
A11: 50008 | B11: LN1008 | C11: C | D11: 2021-08-18 | E11: 2021-08-18 06:00:00
A12: 50009 | B12: LN1009 | C12: C | D12: 2017-04-11 | E12: 2017-04-11 06:00:00
A13: 50010 | B13: LN1010 | C13: C | D13: 2022-10-05 | E13: 2022-10-05 06:00:00
A14: 50011 | B14: LN1011 | C14: C | D14: 2020-02-28 | E14: 2020-02-28 06:00:00
A15: 50012 | B15: LN1012 | C15: C | D15: 2022-05-16 | E15: 2022-05-16 06:00:00
... A54: 50051 | B54: LN1017 | C54: NA | D54: 2026-03-31 | E54: 2026-04-01 06:00:00

Sheet Data - Collateral
A1: Raw source file collsys_collateral.csv as received (contains seeded defects). Also in data/landing/2026-06-30/.
A3: collateral_id | B3: loan_id | C3: collateral_type | D3: collateral_value | E3: valuation_date
A4: CL2001 | B4: LN1001 | C4: EQP | D4: 3000000 | E4: 2025-09-30
A5: CL2002 | B5: LN1003 | C5: ARI | D5: 2500000 | E5: 2026-03-31
A6: CL2003 | B6: LN1004 | C6: OFF | D6: 25000000 | E6: 2025-06-15
A7: CL2004 | B7: LN1005 | C7: EQP | D7: 1800000 | E7: 2025-12-31
A8: CL2005 | B8: LN1007 | C8: MFR | D8: 33000000 | E8: 2025-10-01
A9: CL2006 | B9: LN1009 | C9: RTL | D9: 19000000 | E9: 2023-02-10
A10: CL2007 | B10: LN1011 | C10: IND | D10: 30500000 | E10: 2025-08-20
A11: CL2008 | B11: LN1014 | C11: MFR | D11: 22000000 | E11: 2025-12-05
A12: CL2009 | B12: LN1017 | C12: RTL | D12: 12500000 | E12: 2026-01-15
A13: CL2010 | B13: LN1019 | C13: OFF | D13: 36000000 | E13: 2025-11-20
A14: CL2011 | B14: LN1020 | C14: IND | D14: 21000000 | E14: 2026-02-28
A15: CL2012 | B15: LN1022 | C15: EQP | D15: 3500000 | E15: 2025-07-31
... A27: CL2024 | B27: LN1011 | C27: IND | D27: 2000000 | E27: 2025-08-20

Sheet Data - GL Control
A1: Raw source file gl_control.csv as received (contains seeded defects). Also in data/landing/2026-06-30/.
A3: gl_account | B3: as_of_date | C3: gl_balance
A4: 141000 | B4: 2026-06-30 | C4: 85950000
A5: 142000 | B5: 2026-06-30 | C5: 203050000

Sheet Expected Results
A1: QA answer key: 120 rows (40 loans x 3 scenarios). Check every squad's calculation output against these.
A3: loan_id | B3: portfolio | C3: product | D3: rating | E3: status | F3: scenario | G3: outstanding | H3: undrawn | I3: ead | J3: base_pd | K3: stressed_pd | L3: cum_pd | M3: lgd | N3: loss | O3: rw | P3: rwa | Q3: rate
A4: LN1001 | B4: CI | C4: CI_TERM | D4: 4 | E4: CURRENT | F4: BASE | G4: 4200000 | H4: 1800000 | I4: 5100000 | J4: 0.008 | K4: 0.008 | L4: 0.018 | M4: 0.45 | N4: 41310 | O4: 1 | P4: 5100000 | Q4: 0.0685
A5: LN1001 | B5: CI | C5: CI_TERM | D5: 4 | E5: CURRENT | F5: MOD | G5: 4200000 | H5: 1800000 | I5: 5100000 | J5: 0.008 | K5: 0.0144 | L5: 0.0324 | M5: 0.45 | N5: 74358 | O5: 1 | P5: 5100000 | Q5: 0.0685
A6: LN1001 | B6: CI | C6: CI_TERM | D6: 4 | E6: CURRENT | F6: SEV | G6: 4200000 | H6: 1800000 | I6: 5100000 | J6: 0.008 | K6: 0.024 | L6: 0.054 | M6: 0.45 | N6: 123930 | O6: 1 | P6: 5100000 | Q6: 0.0685
A7: LN1002 | B7: CI | C7: CI_REVOLVER | D7: 4 | E7: CURRENT | F7: BASE | G7: 2600000 | H7: 1400000 | I7: 3300000 | J7: 0.008 | K7: 0.008 | L7: 0.018 | M7: 0.45 | N7: 26730 | O7: 1 | P7: 3300000 | Q7: 0.074
A8: LN1002 | B8: CI | C8: CI_REVOLVER | D8: 4 | E8: CURRENT | F8: MOD | G8: 2600000 | H8: 1400000 | I8: 3300000 | J8: 0.008 | K8: 0.0144 | L8: 0.0324 | M8: 0.45 | N8: 48114 | O8: 1 | P8: 3300000 | Q8: 0.074
A9: LN1002 | B9: CI | C9: CI_REVOLVER | D9: 4 | E9: CURRENT | F9: SEV | G9: 2600000 | H9: 1400000 | I9: 3300000 | J9: 0.008 | K9: 0.024 | L9: 0.054 | M9: 0.45 | N9: 80190 | O9: 1 | P9: 3300000 | Q9: 0.074
A10: LN1003 | B10: CI | C10: CI_REVOLVER | D10: 5 | E10: CURRENT | F10: BASE | G10: 3100000 | H10: 1900000 | I10: 4050000 | J10: 0.02 | K10: 0.02 | L10: 0.045 | M10: 0.444444 | N10: 81000 | O10: 1 | P10: 4050000 | Q10: 0.076
A11: LN1003 | B11: CI | C11: CI_REVOLVER | D11: 5 | E11: CURRENT | F11: MOD | G11: 3100000 | H11: 1900000 | I11: 4050000 | J11: 0.02 | K11: 0.036 | L11: 0.081 | M11: 0.45 | N11: 147622.5 | O11: 1 | P11: 4050000 | Q11: 0.076
A12: LN1003 | B12: CI | C12: CI_REVOLVER | D12: 5 | E12: CURRENT | F12: SEV | G12: 3100000 | H12: 1900000 | I12: 4050000 | J12: 0.02 | K12: 0.06 | L12: 0.135 | M12: 0.45 | N12: 246037.5 | O12: 1 | P12: 4050000 | Q12: 0.076
A13: LN1004 | B13: CRE | C13: CRE_OFFICE | D13: 4 | E13: CURRENT | F13: BASE | G13: 16200000 | H13: 1800000 | I13: 17100000 | J13: 0.008 | K13: 0.008 | L13: 0.018 | M13: 0.1 | N13: 30780 | O13: 1 | P13: 17100000 | Q13: 0.0525
A14: LN1004 | B14: CRE | C14: CRE_OFFICE | D14: 4 | E14: CURRENT | F14: MOD | G14: 16200000 | H14: 1800000 | I14: 17100000 | J14: 0.008 | K14: 0.016 | L14: 0.036 | M14: 0.1 | N14: 61560 | O14: 1 | P14: 17100000 | Q14: 0.0525
A15: LN1004 | B15: CRE | C15: CRE_OFFICE | D15: 4 | E15: CURRENT | F15: SEV | G15: 16200000 | H15: 1800000 | I15: 17100000 | J15: 0.008 | K15: 0.028 | L15: 0.063 | M15: 0.210526 | N15: 226800 | O15: 1 | P15: 17100000 | Q15: 0.0525
... A123: LN1040 | B123: CRE | C123: CRE_MULTIFAMILY | D123: 4 | E123: CURRENT | F123: SEV | G123: 8450000 | H123: 50000 | I123: 8475000 | J123: 0.008 | K123: 0.028 | L123: 0.063 | M123: 0.235398 | N123: 125685 | O123: 1 | P123: 8475000 | Q123: 0.063

Sheet Expected Summary
A1: Portfolio totals from the Expected Results tab (live formulas). Compare with PRD Section 9.
A3: Measure | B3: BASE | C3: MOD | D3: SEV
A4: Total EAD ($) | B4: =SUMIFS('Expected Results'!$I$4:$I$123,'Expected Results'!$F$4:$F$123,"BASE") -> 312400000 | C4: =SUMIFS('Expected Results'!$I$4:$I$123,'Expected Results'!$F$4:$F$123,"MOD") -> 312400000 | D4: =SUMIFS('Expected Results'!$I$4:$I$123,'Expected Results'!$F$4:$F$123,"SEV") -> 312400000
A5: Total RWA ($) | B5: =SUMIFS('Expected Results'!$P$4:$P$123,'Expected Results'!$F$4:$F$123,"BASE") -> 323637500 | C5: =SUMIFS('Expected Results'!$P$4:$P$123,'Expected Results'!$F$4:$F$123,"MOD") -> 323637500 | D5: =SUMIFS('Expected Results'!$P$4:$P$123,'Expected Results'!$F$4:$F$123,"SEV") -> 323637500
A6: Stress loss - C&I ($) | B6: =SUMIFS('Expected Results'!$N$4:$N$123,'Expected Results'!$F$4:$F$123,"BASE",'Expected Results'!$B$4:$B$123,"CI") -> 4599843.7 | C6: =SUMIFS('Expected Results'!$N$4:$N$123,'Expected Results'!$F$4:$F$123,"MOD",'Expected Results'!$B$4:$B$123,"CI") -> 7634936.3 | D6: =SUMIFS('Expected Results'!$N$4:$N$123,'Expected Results'!$F$4:$F$123,"SEV",'Expected Results'!$B$4:$B$123,"CI") -> 12105647
A7: Stress loss - CRE ($) | B7: =SUMIFS('Expected Results'!$N$4:$N$123,'Expected Results'!$F$4:$F$123,"BASE",'Expected Results'!$B$4:$B$123,"CRE") -> 1917080 | C7: =SUMIFS('Expected Results'!$N$4:$N$123,'Expected Results'!$F$4:$F$123,"MOD",'Expected Results'!$B$4:$B$123,"CRE") -> 4227560 | D7: =SUMIFS('Expected Results'!$N$4:$N$123,'Expected Results'!$F$4:$F$123,"SEV",'Expected Results'!$B$4:$B$123,"CRE") -> 12074407
A8: Stress loss - total ($) | B8: =SUMIFS('Expected Results'!$N$4:$N$123,'Expected Results'!$F$4:$F$123,"BASE") -> 6516923.7 | C8: =SUMIFS('Expected Results'!$N$4:$N$123,'Expected Results'!$F$4:$F$123,"MOD") -> 11862496 | D8: =SUMIFS('Expected Results'!$N$4:$N$123,'Expected Results'!$F$4:$F$123,"SEV") -> 24180054
A9: Loss rate (% of EAD) | B9: =IFERROR(B8/B4,0) -> 0.020860831 | C9: =IFERROR(C8/C4,0) -> 0.037972139 | D9: =IFERROR(D8/D4,0) -> 0.07740094
A11: Loan count per scenario | B11: =COUNTIF('Expected Results'!$F$4:$F$123,"BASE") -> 40 | C11: =COUNTIF('Expected Results'!$F$4:$F$123,"MOD") -> 40 | D11: =COUNTIF('Expected Results'!$F$4:$F$123,"SEV") -> 40
A13: Capital results (from PRD Section 9.10; produced by scripts/generate_sample_data.py)
A14: PPNR, 9 quarters ($) | B14: 12998025 | C14: 11048321 | D14: 7798815
A15: Ending CET1 ($) | B15: 61020070 | C15: 55256802 | D15: 42958821
A16: Ending CET1 ratio | B16: 0.1212 | C16: 0.1097 | D16: 0.0853
